mainsequence/__init__.py
mainsequence/__main__.py
mainsequence/logconf.py
mainsequence/cli/__init__.py
mainsequence/cli/api.py
mainsequence/cli/cli.py
mainsequence/cli/config.py
mainsequence/cli/ssh_utils.py
mainsequence/client/__init__.py
mainsequence/client/base.py
mainsequence/client/exceptions.py
mainsequence/client/models_helpers.py
mainsequence/client/models_tdag.py
mainsequence/client/models_vam.py
mainsequence/client/utils.py
mainsequence/client/data_sources_interfaces/__init__.py
mainsequence/client/data_sources_interfaces/duckdb.py
mainsequence/client/data_sources_interfaces/timescale.py
mainsequence/dashboards/__init__.py
mainsequence/dashboards/streamlit/__init__.py
mainsequence/dashboards/streamlit/scaffold.py
mainsequence/dashboards/streamlit/assets/config.toml
mainsequence/dashboards/streamlit/assets/favicon.png
mainsequence/dashboards/streamlit/assets/image_1_base64.txt
mainsequence/dashboards/streamlit/assets/image_2_base64.txt
mainsequence/dashboards/streamlit/assets/image_3_base64.txt
mainsequence/dashboards/streamlit/assets/image_4_base64.txt
mainsequence/dashboards/streamlit/assets/image_5_base64.txt
mainsequence/dashboards/streamlit/assets/logo.png
mainsequence/dashboards/streamlit/core/__init__.py
mainsequence/dashboards/streamlit/core/theme.py
mainsequence/dashboards/streamlit/pages/__init__.py
mainsequence/instrumentation/__init__.py
mainsequence/instrumentation/utils.py
mainsequence/instruments/__init__.py
mainsequence/instruments/instruments.default.toml
mainsequence/instruments/settings.py
mainsequence/instruments/utils.py
mainsequence/instruments/data_interface/__init__.py
mainsequence/instruments/data_interface/data_interface.py
mainsequence/instruments/instruments/__init__.py
mainsequence/instruments/instruments/base_instrument.py
mainsequence/instruments/instruments/bond.py
mainsequence/instruments/instruments/european_option.py
mainsequence/instruments/instruments/interest_rate_swap.py
mainsequence-3.10.8.dist-info/licenses/LICENSE
mainsequence-3.10.8.dist-info/METADATA
mainsequence-3.10.8.dist-info/WHEEL
mainsequence-3.10.8.dist-info/entry_points.txt
mainsequence-3.10.8.dist-info/top_level.txt
mainsequence-3.10.8.dist-info/RECORD
