Metadata-Version: 2.4
Name: mainsequence
Version: 3.10.8
Summary: Main Sequence SDK 
Author-email: Main Sequence GmbH <dev@main-sequence.io>
License: MainSequence GmbH SDK License Agreement
Project-URL: Homepage, https://github.com/mainsequence-sdk/mainsequence-sdk
Project-URL: Issues, https://github.com/mainsequence-sdk/mainsequence-sdk/issues
Classifier: Programming Language :: Python :: 3
Classifier: Programming Language :: Python :: 3 :: Only
Classifier: License :: OSI Approved :: MIT License
Classifier: Operating System :: OS Independent
Requires-Python: >=3.10
License-File: LICENSE
Requires-Dist: cloudpickle
Requires-Dist: cryptography
Requires-Dist: fire
Requires-Dist: google-auth
Requires-Dist: joblib
Requires-Dist: matplotlib
Requires-Dist: nbconvert
Requires-Dist: numexpr
Requires-Dist: opentelemetry-api
Requires-Dist: opentelemetry-exporter-otlp
Requires-Dist: opentelemetry-sdk
Requires-Dist: pandas
Requires-Dist: pandas-market-calendars
Requires-Dist: psutil
Requires-Dist: pyarrow
Requires-Dist: pydantic
Requires-Dist: python-binance
Requires-Dist: python-dotenv
Requires-Dist: python-logstash
Requires-Dist: pyyaml
Requires-Dist: s3fs
Requires-Dist: scikit-learn
Requires-Dist: scipy
Requires-Dist: structlog
Requires-Dist: tqdm
Requires-Dist: docstring-parser
Requires-Dist: concurrent-log-handler
Requires-Dist: duckdb
Requires-Dist: plotly
Requires-Dist: typer
Requires-Dist: QuantLib
Requires-Dist: streamlit
Dynamic: license-file
